ForestDiffusion/__init__.py
ForestDiffusion/diffusion_with_trees_class.py
ForestDiffusion/utils/__init__.py
ForestDiffusion/utils/diffusion.py
ForestDiffusion/utils/utils_diffusion.py
ForestDiffusion-1.0.6.dist-info/LICENSE.txt
ForestDiffusion-1.0.6.dist-info/METADATA
ForestDiffusion-1.0.6.dist-info/WHEEL
ForestDiffusion-1.0.6.dist-info/top_level.txt
ForestDiffusion-1.0.6.dist-info/RECORD
