Metadata-Version: 2.1
Name: ForestDiffusion
Version: 1.0.6
Summary: Generating and Imputing Tabular Data via Diffusion and Flow XGBoost Models
Home-page: https://github.com/SamsungSAILMontreal/ForestDiffusion
Author: Alexia Jolicoeur-Martineau
Author-email: <alexia.jolicoeur-martineau@mail.mcgill.ca>
Keywords: python,AI,xgboost,GBT,tree,forest,tabular,diffusion,flow
Classifier: Development Status :: 3 - Alpha
Classifier: Intended Audience :: Education
Classifier: Programming Language :: Python :: 2
Classifier: Programming Language :: Python :: 3
Classifier: Operating System :: MacOS :: MacOS X
Classifier: Operating System :: Microsoft :: Windows
License-File: LICENSE.txt
Requires-Dist: numpy
Requires-Dist: scikit-learn
Requires-Dist: xgboost >=2.0.0
Requires-Dist: lightgbm
Requires-Dist: catboost
Requires-Dist: pandas
